{
  "questions": [
    {
      "id": 1,
      "question": "OSI 7 계층은 데이터를 캡슐화하여 ___ 형태로 송수신한다.",
      "answer": "PDU"
    },
    {
      "id": 2,
      "question": "네트워크 계층은 데이터 전송을 위해 ___ 주소를 사용한다.",
      "answer": "IP"
    },
    {
      "id": 3,
      "question": "Transport 계층은 데이터 흐름을 제어하고 ___를(을) 사용한다.",
      "answer": "포트 번호"
    },
    {
      "id": 4,
      "question": "데이터링크 계층에서 송수신되는 데이터 단위는 ___이다.",
      "answer": "프레임"
    },
    {
      "id": 5,
      "question": "TCP/IP 프로토콜 스택은 ___ 계층으로 구성된다.",
      "answer": "4"
    },
    {
      "id": 6,
      "question": "HTTP는 ___ 계층에서 동작하는 프로토콜이다.",
      "answer": "Application"
    },
    {
      "id": 7,
      "question": "TCP는 데이터 전송의 신뢰성을 보장하기 위해 ___를(을) 사용한다.",
      "answer": "ACK"
    },
    {
      "id": 8,
      "question": "정적 라우팅은 관리자가 ___을(를) 수동으로 설정한다.",
      "answer": "라우팅 테이블"
    },
    {
      "id": 9,
      "question": "UDP는 TCP에 비해 ___ 속성이 부족하다.",
      "answer": "신뢰성"
    },
    {
      "id": 10,
      "question": "패킷 스위칭 시스템은 데이터를 작은 단위로 나누어 ___으로 전송한다.",
      "answer": "패킷"
    },
    {
      "id": 11,
      "question": "DNS는 ___ 계층에서 동작하는 프로토콜이다.",
      "answer": "Application"
    },
    {
      "id": 12,
      "question": "PDU는 각 ___에서 사용하는 데이터 단위를 의미한다.",
      "answer": "계층"
    },
    {
      "id": 13,
      "question": "네트워크 계층에서 사용하는 주요 프로토콜은 ___이다.",
      "answer": "IP"
    },
    {
      "id": 14,
      "question": "HTTPS는 TCP 포트 ___번을 사용한다.",
      "answer": "443"
    },
    {
      "id": 15,
      "question": "OSI 7 계층의 Presentation 계층은 데이터를 ___하고 압축한다.",
      "answer": "암호화"
    }
  ]
}
